MANIFEST.in
setup.cfg
setup.py
pyRiffle.egg-info/PKG-INFO
pyRiffle.egg-info/SOURCES.txt
pyRiffle.egg-info/dependency_links.txt
pyRiffle.egg-info/entry_points.txt
pyRiffle.egg-info/pbr.json
pyRiffle.egg-info/requires.txt
pyRiffle.egg-info/top_level.txt
riffle/__init__.py
riffle/crust.py
riffle/cumin.py
riffle/exis.py
riffle/model.py
riffle/utils.py
riffle/Darwin-x86_64/pymantle.so
riffle/linux-386/pymantle.so
riffle/linux-x86_64/pymantle.so
test/test_cumin.py
test/test_model.py
test/test_schema.py