Metadata-Version: 1.1
Name: pyRiffle
Version: 0.2.6
Summary: Riffle client libraries for interacting over a fabric
Home-page: http://www.exis.io
Author: Exis
Author-email: UNKNOWN
License: MIT
Platform: UNKNOWN
Classifier: Intended Audience :: Developers
Classifier: License :: OSI Approved :: MIT License
Classifier: Natural Language :: English
Classifier: Programming Language :: Python
Classifier: Programming Language :: Python :: 2.7
Classifier: Topic :: Software Development :: Libraries :: Python Modules
